[{"keyword":"Feature","name":"Add product to cart","line":1,"description":"","id":"add-product-to-cart","uri":"C:\\RubymineProjects\\page-object_framework\\features\\ShippingAddress.feature","elements":[{"keyword":"Scenario","name":"Verify address and verify shipping address","line":3,"description":"","id":"add-product-to-cart;verify-address-and-verify-shipping-address","type":"scenario","steps":[{"keyword":"When ","name":"I open automationpractice website","line":4,"match":{"location":"features/step_definitions/shopping_cart.rb:1"},"result":{"status":"skipped","duration":15625000}},{"keyword":"And ","name":"I login using data from yml","line":5,"match":{"location":"features/step_definitions/shopping_cart.rb:5"},"result":{"status":"skipped","duration":0}},{"keyword":"And ","name":"I hover on women menu item and click summer dresses","line":6,"match":{"location":"features/step_definitions/shopping_cart.rb:19"},"result":{"status":"skipped","duration":15625000}},{"keyword":"And ","name":"I add a summer dress to cart","line":7,"match":{"location":"features/step_definitions/shopping_cart.rb:26"},"result":{"status":"skipped","duration":0}},{"keyword":"And ","name":"verify the item and price","line":8,"match":{"location":"features/step_definitions/shopping_cart.rb:34"},"result":{"status":"skipped","duration":0}},{"keyword":"And ","name":"I verify the address and proceed","line":9,"match":{"location":"features/step_definitions/shopping_cart.rb:39"},"result":{"status":"skipped","duration":15625000}},{"keyword":"Then ","name":"I verify shipping address and proceed","line":10,"match":{"location":"features/step_definitions/shopping_cart.rb:45"},"result":{"status":"skipped","duration":0}}]}]}]